blissclient/__init__.py
blissclient/client.py
blissclient/exceptions.py
blissclient/py.typed
blissclient/utils.py
blissclient/high_level/__init__.py
blissclient/high_level/base.py
blissclient/high_level/events.py
blissclient/high_level/hardware.py
blissclient/high_level/info.py
blissclient/high_level/jsonready.py
blissclient/high_level/scan.py
blissclient/high_level/session.py
blissclient/openapi/__init__.py
blissclient/openapi/api_config.py
blissclient/openapi/models/CallFunction.py
blissclient/openapi/models/CallFunctionAsyncState.py
blissclient/openapi/models/CallFunctionResponse.py
blissclient/openapi/models/CouldNotRegisterErrorResponse.py
blissclient/openapi/models/ErrorResponse.py
blissclient/openapi/models/InfoSchema.py
blissclient/openapi/models/LockedDict.py
blissclient/openapi/models/ObjectError.py
blissclient/openapi/models/ObjectSchema.py
blissclient/openapi/models/ObjectTypeSchema.py
blissclient/openapi/models/Paginated_ObjectSchema_.py
blissclient/openapi/models/Paginated_ObjectTypeSchema_.py
blissclient/openapi/models/RegisterHardwareSchema.py
blissclient/openapi/models/SetObjectProperty.py
blissclient/openapi/models/ValidationErrorModel.py
blissclient/openapi/models/YamlContentSchema.py
blissclient/openapi/models/__init__.py
blissclient/openapi/services/BeaconApi_service.py
blissclient/openapi/services/CallApi_service.py
blissclient/openapi/services/InfoApi_service.py
blissclient/openapi/services/ObjectApi_service.py
blissclient/openapi/services/ObjectTypeApi_service.py
blissclient/openapi/services/__init__.py
blissclient/openapi/services/async_BeaconApi_service.py
blissclient/openapi/services/async_CallApi_service.py
blissclient/openapi/services/async_InfoApi_service.py
blissclient/openapi/services/async_ObjectApi_service.py
blissclient/openapi/services/async_ObjectTypeApi_service.py
blissclient-1.2.2.dist-info/METADATA
blissclient-1.2.2.dist-info/WHEEL
blissclient-1.2.2.dist-info/top_level.txt
blissclient-1.2.2.dist-info/RECORD
