Metadata-Version: 2.4
Name: blissclient
Version: 1.2.2
Summary: A python client library for the bliss REST API
Author-email: ESRF <bcu@esrf.fr>
License-Expression: MIT
Project-URL: Homepage, https://gitlab.esrf.fr/bliss/blissclient
Project-URL: Bug Tracker, https://gitlab.esrf.fr/bliss/blissclient/issues
Classifier: Intended Audience :: Science/Research
Classifier: Programming Language :: Python :: 3
Requires-Python: >=3.10
Requires-Dist: httpx
Requires-Dist: pydantic>=2
Requires-Dist: python-socketio[client]>=5.11
Requires-Dist: tblib
Provides-Extra: test
Requires-Dist: pytest>=7; extra == "test"
Requires-Dist: pint; extra == "test"
Provides-Extra: dev
Requires-Dist: black>=24; extra == "dev"
Requires-Dist: flake8>=4; extra == "dev"
Requires-Dist: flake8-pyproject; extra == "dev"
